{
 "geoms": {
 "geom1_ribbon_g19": {
 "geom": "ribbon",
"data": "geom1_ribbon_g19.csv",
"aes": {
 "x": "clarity",
"y": "..count..",
"group": "cut",
"colour": "cut",
"fill": "cut" 
},
"params": {
 "na.rm": false 
},
"update": "",
"subord": [
 "group" 
],
"subvars": {
 "group": "cut" 
},
"classed": "geom1_ribbon_g19",
"types": {
 "colour": "rgb",
"fill": "rgb",
"y": "numeric",
"x": "numeric",
"density": "numeric",
"scaled": "numeric",
"count": "numeric",
"group": "integer",
"PANEL": "integer",
"ymin": "numeric",
"ymax": "numeric",
"xmin": "numeric",
"xmax": "numeric" 
} 
} 
},
"selectors": [],
"plots": {
 "g19": {
 "geoms": [
 "geom1_ribbon_g19" 
],
"scales": {
 "colour": [ "#F8766D", "#A3A500", "#00BF7D", "#00B0F6", "#E76BF3" ],
"fill": [ "#F8766D", "#A3A500", "#00BF7D", "#00B0F6", "#E76BF3" ] 
},
"options": {
 "width":    400,
"height":    400 
},
"axis": {
 "x": [ 0.073171, 0.19512, 0.31707, 0.43902, 0.56098, 0.68293, 0.80488, 0.92683 ],
"xlab": [ "I1", "SI2", "SI1", "VS2", "VS1", "VVS2", "VVS1", "IF" ],
"xrange": [    0.4,    8.6 ],
"xname": "clarity",
"xline": true,
"xticks": true,
"y": [ 0.045455, 0.38002, 0.71458 ],
"ylab": [ "0", "10000", "20000" ],
"yrange": [ -1358.6,  28531 ],
"yname": "count",
"yline": true,
"yticks": true 
},
"title": "geom_area",
"legend": {
 "cut": {
 "guide": "legend",
"geoms": "polygon",
"title": "cut",
"entries": [
 {
 "polygoncolour": "#E76BF3",
"polygonfill": "#E76BF3",
"polygonsize":    0.5,
"polygonlinetype":      1,
"polygonorder": 5,
"label": [ "Ideal" ] 
},
{
 "polygoncolour": "#00B0F6",
"polygonfill": "#00B0F6",
"polygonsize":    0.5,
"polygonlinetype":      1,
"polygonorder": 4,
"label": [ "Premium" ] 
},
{
 "polygoncolour": "#00BF7D",
"polygonfill": "#00BF7D",
"polygonsize":    0.5,
"polygonlinetype":      1,
"polygonorder": 3,
"label": [ "Very Good" ] 
},
{
 "polygoncolour": "#A3A500",
"polygonfill": "#A3A500",
"polygonsize":    0.5,
"polygonlinetype":      1,
"polygonorder": 2,
"label": [ "Good" ] 
},
{
 "polygoncolour": "#F8766D",
"polygonfill": "#F8766D",
"polygonsize":    0.5,
"polygonlinetype":      1,
"polygonorder": 1,
"label": [ "Fair" ] 
} 
] 
} 
} 
} 
} 
}